django_migrate_or_rollback/__init__.py
django_migrate_or_rollback/management/__init__.py
django_migrate_or_rollback/management/commands/__init__.py
django_migrate_or_rollback/management/commands/migrate_or_rollback.py
django_migrate_or_rollback-0.1.0.dist-info/licenses/LICENSE
django_migrate_or_rollback-0.1.0.dist-info/METADATA
django_migrate_or_rollback-0.1.0.dist-info/WHEEL
django_migrate_or_rollback-0.1.0.dist-info/top_level.txt
django_migrate_or_rollback-0.1.0.dist-info/RECORD
