Metadata-Version: 2.4
Name: django-migrate-or-rollback
Version: 0.1.0
Summary: Management command to attempt Django migrations and rollback on failure
Author-email: "Zagaran, Inc." <info@zagaran.com>
License-Expression: MIT
Project-URL: Homepage, https://github.com/zagaran/django-migrate-or-rollback
Keywords: django,migrations
Classifier: Programming Language :: Python :: 3
Classifier: Operating System :: OS Independent
Requires-Python: >=3.6
License-File: LICENSE
Requires-Dist: django>=2.0
Dynamic: license-file
